[
  {
    "inBlock": 35707,
    "createdAt": "2021-08-26T17:12:22.796Z",
    "network": "OLYMPIA",
    "memberId": "37"
  },
  {
    "inBlock": 27085,
    "createdAt": "2021-08-26T19:59:55.225Z",
    "network": "OLYMPIA",
    "memberId": "11"
  },
  {
    "inBlock": 34533,
    "createdAt": "2021-09-20T16:38:23.442Z",
    "network": "OLYMPIA",
    "memberId": "7"
  },
  {
    "inBlock": 31273,
    "createdAt": "2021-09-17T13:56:34.618Z",
    "network": "OLYMPIA",
    "memberId": "2"
  },
  {
    "inBlock": 95460,
    "createdAt": "2021-10-12T13:07:00.684Z",
    "network": "OLYMPIA",
    "memberId": "14"
  },
  {
    "inBlock": 5251,
    "createdAt": "2021-08-11T15:56:43.831Z",
    "network": "OLYMPIA",
    "memberId": "28"
  },
  {
    "inBlock": 73763,
    "createdAt": "2021-10-24T11:05:54.962Z",
    "network": "OLYMPIA",
    "memberId": "31"
  },
  {
    "inBlock": 93833,
    "createdAt": "2021-07-12T23:33:39.313Z",
    "network": "OLYMPIA",
    "memberId": "7"
  },
  {
    "inBlock": 85222,
    "createdAt": "2021-10-12T21:06:08.569Z",
    "network": "OLYMPIA",
    "memberId": "39"
  },
  {
    "inBlock": 33650,
    "createdAt": "2021-08-13T00:25:08.019Z",
    "network": "OLYMPIA",
    "memberId": "18"
  }
]
