[
  {
    "id": "0",
    "inBlock": 62733,
    "createdAt": "2021-09-09T00:01:03.920Z",
    "network": "OLYMPIA",
    "groupId": "membershipWorkingGroup",
    "workerId": "membershipWorkingGroup-71",
    "rewardAccount": "5GNJqTPyNqANBkUVMN1LPPrxXnFouWXoe2wNSmmEoLctxiZY",
    "amount": 8780,
    "type": "REGULAR"
  },
  {
    "id": "1",
    "inBlock": 3844,
    "createdAt": "2021-10-30T09:39:33.028Z",
    "network": "OLYMPIA",
    "groupId": "membershipWorkingGroup",
    "workerId": "membershipWorkingGroup-73",
    "rewardAccount": "5GNJqTPyNqANBkUVMN1LPPrxXnFouWXoe2wNSmmEoLctxiZY",
    "amount": 3190,
    "type": "REGULAR"
  },
  {
    "id": "2",
    "inBlock": 90343,
    "createdAt": "2021-07-21T07:56:38.220Z",
    "network": "OLYMPIA",
    "groupId": "storageWorkingGroup",
    "workerId": "storageWorkingGroup-21",
    "rewardAccount": "5GNJqTPyNqANBkUVMN1LPPrxXnFouWXoe2wNSmmEoLctxiZY",
    "amount": 2860,
    "type": "REGULAR"
  },
  {
    "id": "3",
    "inBlock": 83855,
    "createdAt": "2021-10-17T01:10:32.893Z",
    "network": "OLYMPIA",
    "groupId": "contentDirectoryWorkingGroup",
    "workerId": "contentDirectoryWorkingGroup-50",
    "rewardAccount": "5GNJqTPyNqANBkUVMN1LPPrxXnFouWXoe2wNSmmEoLctxiZY",
    "amount": 2670,
    "type": "REGULAR"
  },
  {
    "id": "4",
    "inBlock": 22480,
    "createdAt": "2021-07-14T19:43:49.917Z",
    "network": "OLYMPIA",
    "groupId": "contentDirectoryWorkingGroup",
    "workerId": "contentDirectoryWorkingGroup-48",
    "rewardAccount": "5GNJqTPyNqANBkUVMN1LPPrxXnFouWXoe2wNSmmEoLctxiZY",
    "amount": 5740,
    "type": "REGULAR"
  },
  {
    "id": "5",
    "inBlock": 29629,
    "createdAt": "2021-10-11T01:47:03.470Z",
    "network": "OLYMPIA",
    "groupId": "storageWorkingGroup",
    "workerId": "storageWorkingGroup-23",
    "rewardAccount": "5GNJqTPyNqANBkUVMN1LPPrxXnFouWXoe2wNSmmEoLctxiZY",
    "amount": 9310,
    "type": "REGULAR"
  },
  {
    "id": "6",
    "inBlock": 63451,
    "createdAt": "2021-10-10T17:37:55.987Z",
    "network": "OLYMPIA",
    "groupId": "storageWorkingGroup",
    "workerId": "storageWorkingGroup-38",
    "rewardAccount": "5GNJqTPyNqANBkUVMN1LPPrxXnFouWXoe2wNSmmEoLctxiZY",
    "amount": 7160,
    "type": "REGULAR"
  },
  {
    "id": "7",
    "inBlock": 28380,
    "createdAt": "2021-07-04T08:27:45.818Z",
    "network": "OLYMPIA",
    "groupId": "membershipWorkingGroup",
    "workerId": "membershipWorkingGroup-80",
    "rewardAccount": "5GNJqTPyNqANBkUVMN1LPPrxXnFouWXoe2wNSmmEoLctxiZY",
    "amount": 8730,
    "type": "REGULAR"
  },
  {
    "id": "8",
    "inBlock": 7644,
    "createdAt": "2021-11-25T23:10:02.102Z",
    "network": "OLYMPIA",
    "groupId": "membershipWorkingGroup",
    "workerId": "membershipWorkingGroup-64",
    "rewardAccount": "5GNJqTPyNqANBkUVMN1LPPrxXnFouWXoe2wNSmmEoLctxiZY",
    "amount": 1110,
    "type": "REGULAR"
  },
  {
    "id": "9",
    "inBlock": 40420,
    "createdAt": "2021-10-01T18:52:47.162Z",
    "network": "OLYMPIA",
    "groupId": "membershipWorkingGroup",
    "workerId": "membershipWorkingGroup-74",
    "rewardAccount": "5GNJqTPyNqANBkUVMN1LPPrxXnFouWXoe2wNSmmEoLctxiZY",
    "amount": 4050,
    "type": "REGULAR"
  }
]
