[
  {
    "createdAt": "2021-07-15T04:08:59.372Z",
    "groupId": "contentDirectoryWorkingGroup",
    "workerId": "contentDirectoryWorkingGroup-35",
    "amount": 6735
  },
  {
    "createdAt": "2021-07-10T09:13:28.174Z",
    "groupId": "membershipWorkingGroup",
    "workerId": "membershipWorkingGroup-64",
    "amount": 5392
  },
  {
    "createdAt": "2021-07-13T22:09:10.618Z",
    "groupId": "storageWorkingGroup",
    "workerId": "storageWorkingGroup-28",
    "amount": 1964
  },
  {
    "createdAt": "2021-07-15T16:23:17.990Z",
    "groupId": "contentDirectoryWorkingGroup",
    "workerId": "contentDirectoryWorkingGroup-37",
    "amount": 3525
  },
  {
    "createdAt": "2021-07-10T12:48:13.142Z",
    "groupId": "forumWorkingGroup",
    "workerId": "forumWorkingGroup-6",
    "amount": 5026
  },
  {
    "createdAt": "2021-07-10T10:30:39.999Z",
    "groupId": "forumWorkingGroup",
    "workerId": "forumWorkingGroup-5",
    "amount": 2469
  },
  {
    "createdAt": "2021-07-14T13:35:45.017Z",
    "groupId": "forumWorkingGroup",
    "workerId": "forumWorkingGroup-22",
    "amount": 8068
  },
  {
    "createdAt": "2021-07-09T15:24:51.957Z",
    "groupId": "forumWorkingGroup",
    "workerId": "forumWorkingGroup-21",
    "amount": 9459
  },
  {
    "createdAt": "2021-07-12T13:24:41.013Z",
    "groupId": "storageWorkingGroup",
    "workerId": "storageWorkingGroup-29",
    "amount": 4324
  },
  {
    "createdAt": "2021-07-13T01:58:43.805Z",
    "groupId": "membershipWorkingGroup",
    "workerId": "membershipWorkingGroup-61",
    "amount": 9508
  }
]
