[
  {
    "createdAt": "2021-07-06T03:36:06.896Z",
    "groupId": "membershipWorkingGroup",
    "workerId": "membershipWorkingGroup-63",
    "amount": 5555
  },
  {
    "createdAt": "2021-07-11T16:52:16.981Z",
    "groupId": "forumWorkingGroup",
    "workerId": "forumWorkingGroup-11",
    "amount": 2793
  },
  {
    "createdAt": "2021-07-08T02:58:35.567Z",
    "groupId": "storageWorkingGroup",
    "workerId": "storageWorkingGroup-25",
    "amount": 7036
  },
  {
    "createdAt": "2021-07-07T19:01:08.637Z",
    "groupId": "forumWorkingGroup",
    "workerId": "forumWorkingGroup-7",
    "amount": 625
  },
  {
    "createdAt": "2021-07-06T12:30:07.538Z",
    "groupId": "storageWorkingGroup",
    "workerId": "storageWorkingGroup-32",
    "amount": 2410
  },
  {
    "createdAt": "2021-07-11T16:44:57.163Z",
    "groupId": "membershipWorkingGroup",
    "workerId": "membershipWorkingGroup-75",
    "amount": 1342
  },
  {
    "createdAt": "2021-07-08T22:48:54.253Z",
    "groupId": "storageWorkingGroup",
    "workerId": "storageWorkingGroup-42",
    "amount": 190
  },
  {
    "createdAt": "2021-07-11T06:54:52.287Z",
    "groupId": "storageWorkingGroup",
    "workerId": "storageWorkingGroup-33",
    "amount": 2022
  },
  {
    "createdAt": "2021-07-05T14:56:06.740Z",
    "groupId": "storageWorkingGroup",
    "workerId": "storageWorkingGroup-30",
    "amount": 9512
  },
  {
    "createdAt": "2021-07-11T08:39:11.138Z",
    "groupId": "storageWorkingGroup",
    "workerId": "storageWorkingGroup-24",
    "amount": 8780
  }
]
