[
  {
    "createdAt": "2021-07-22T16:03:42.463Z",
    "groupId": "forumWorkingGroup",
    "workerId": "forumWorkingGroup-5",
    "amount": 4491
  },
  {
    "createdAt": "2021-07-26T06:54:07.056Z",
    "groupId": "contentDirectoryWorkingGroup",
    "workerId": "contentDirectoryWorkingGroup-54",
    "amount": 6778
  },
  {
    "createdAt": "2021-07-23T22:57:12.072Z",
    "groupId": "forumWorkingGroup",
    "workerId": "forumWorkingGroup-16",
    "amount": 4724
  },
  {
    "createdAt": "2021-07-25T05:04:42.239Z",
    "groupId": "storageWorkingGroup",
    "workerId": "storageWorkingGroup-38",
    "amount": 9739
  },
  {
    "createdAt": "2021-07-23T23:19:15.832Z",
    "groupId": "forumWorkingGroup",
    "workerId": "forumWorkingGroup-22",
    "amount": 2058
  },
  {
    "createdAt": "2021-07-25T08:34:41.900Z",
    "groupId": "contentDirectoryWorkingGroup",
    "workerId": "contentDirectoryWorkingGroup-50",
    "amount": 7470
  },
  {
    "createdAt": "2021-07-20T12:47:05.442Z",
    "groupId": "forumWorkingGroup",
    "workerId": "forumWorkingGroup-11",
    "amount": 8229
  },
  {
    "createdAt": "2021-07-19T10:03:05.510Z",
    "groupId": "membershipWorkingGroup",
    "workerId": "membershipWorkingGroup-70",
    "amount": 3216
  },
  {
    "createdAt": "2021-07-24T11:04:17.014Z",
    "groupId": "contentDirectoryWorkingGroup",
    "workerId": "contentDirectoryWorkingGroup-67",
    "amount": 9193
  },
  {
    "createdAt": "2021-07-25T13:39:18.176Z",
    "groupId": "membershipWorkingGroup",
    "workerId": "membershipWorkingGroup-69",
    "amount": 2097
  }
]
